extended_setup.py
extended_setup_tools-0.2.5.dist-info/licenses/LICENSE
extended_setup_tools-0.2.5.dist-info/METADATA
extended_setup_tools-0.2.5.dist-info/WHEEL
extended_setup_tools-0.2.5.dist-info/top_level.txt
extended_setup_tools-0.2.5.dist-info/RECORD
