Metadata-Version: 2.4
Name: extended-setup-tools
Version: 0.2.5
Summary: Python tool for helping making shorter and smarter setup.py scripts
Home-page: https://gitlab.com/Hares-Lab/tools/extended-setup-tools
Author: Peter Zaitcev / USSX Hares
Maintainer: Peter Zaitcev / USSX Hares
License: BSD 2-clause
Classifier: Development Status :: 4 - Beta
Classifier: License :: OSI Approved :: BSD License
Classifier: Intended Audience :: Developers
Classifier: Natural Language :: English
Classifier: Operating System :: OS Independent
Classifier: Programming Language :: Python :: 3.6
Classifier: Programming Language :: Python :: 3.7
Classifier: Programming Language :: Python :: 3.8
Classifier: Programming Language :: Python :: 3.9
Classifier: Programming Language :: Python :: 3.10
Classifier: Programming Language :: Python :: 3.11
Classifier: Programming Language :: Python :: 3.12
Classifier: Programming Language :: Python :: 3.13
Classifier: Topic :: Software Development :: Build Tools
Classifier: Topic :: Software Development :: Libraries
Classifier: Topic :: Software Development :: Libraries :: Python Modules
Classifier: Topic :: Utilities
Requires-Python: >=3.6
License-File: LICENSE
Requires-Dist: setuptools>=72.2.0; python_version >= "3.8"
Requires-Dist: setuptools; python_version < "3.8"
Requires-Dist: typing_extensions>=4.1.4; python_version >= "3.8"
Provides-Extra: test
Requires-Dist: html-testRunner; extra == "test"
Requires-Dist: lxml; extra == "test"
Requires-Dist: unittest-xml-reporting; extra == "test"
Provides-Extra: all
Requires-Dist: html-testRunner; extra == "all"
Requires-Dist: lxml; extra == "all"
Requires-Dist: unittest-xml-reporting; extra == "all"
Dynamic: author
Dynamic: classifier
Dynamic: description
Dynamic: description-content-type
Dynamic: home-page
Dynamic: license
Dynamic: license-file
Dynamic: maintainer
Dynamic: provides-extra
Dynamic: requires-dist
Dynamic: requires-python
Dynamic: summary
